main.py
setup.py
HLLM.egg-info/PKG-INFO
HLLM.egg-info/SOURCES.txt
HLLM.egg-info/dependency_links.txt
HLLM.egg-info/requires.txt
HLLM.egg-info/top_level.txt